alparc/__init__.py
alparc/cli.py
alparc/eval.py
alparc/io.py
alparc/controls/__init__.py
alparc/controls/common.py
alparc/controls/filter.py
alparc/core/__init__.py
alparc/core/lexicon.py
alparc/core/phoneme.py
alparc/core/stream.py
alparc/core/syllable.py
alparc/core/word.py
alparc/data/data_cleanup.ipynb
alparc/data/example_external_lexicon.txt
alparc/data/example_external_stream.txt
alparc/data/phonemes.csv
alparc/data/english/syllable_frequency.csv
alparc/data/english/syllable_frequency_positions.csv
alparc/data/english/syllables.csv
alparc/data/english/orig/EFS.CD
alparc/data/english/orig/README.txt
alparc/data/german/bigrams.csv
alparc/data/german/syllables.csv
alparc/data/german/trigrams.csv
alparc/data/german/unigrams.csv
alparc/data/german/orig/german_IPA_seg.csv
alparc/data/german/orig/ipa_bigrams_german.csv
alparc/data/german/orig/ipa_trigrams_german.csv
alparc/data/german/orig/link_corpus.txt
alparc/data/german/orig/syll.txt
alparc/phonecodes/__init__.py
alparc/phonecodes/phonecode_tables.py
alparc/phonecodes/phonecodes.py
alparc/phonecodes/pronlex.py
alparc/types/__init__.py
alparc/types/base_types.py
alparc/types/elements.py
alparc/types/lexicon.py
alparc/types/phoneme.py
alparc/types/registers.py
alparc/types/stream.py
alparc/types/syllable.py
alparc/types/word.py
alparc-0.0.8.dist-info/licenses/LICENSE
alparc-0.0.8.dist-info/METADATA
alparc-0.0.8.dist-info/WHEEL
alparc-0.0.8.dist-info/entry_points.txt
alparc-0.0.8.dist-info/top_level.txt
alparc-0.0.8.dist-info/RECORD
