Metadata-Version: 2.4
Name: alparc
Version: 0.0.8
Summary: Artificial languages with rhythmicity, phonological, and acoustic controls
Author: Lorenzo Titone
Author-email: Nikola Milosevic <milose.nik@gmail.com>
Project-URL: Homepage, https://github.com/milosen/alparc
Project-URL: Issues, https://github.com/milosen/alparc/issues
Classifier: Programming Language :: Python :: 3
Classifier: Operating System :: OS Independent
Requires-Python: >=3.8
License-File: LICENSE
Requires-Dist: tyro
Requires-Dist: tqdm
Requires-Dist: seaborn
Requires-Dist: pandas
Requires-Dist: pyyaml
Requires-Dist: pingouin
Requires-Dist: pydantic
Provides-Extra: test
Requires-Dist: pytest; extra == "test"
Dynamic: license-file
